pubkeeper/brew/websocket/__init__.py
pubkeeper/brew/websocket/brew.py
pubkeeper/brew/websocket/patron.py
pubkeeper/brew/websocket/protocols/__init__.py
pubkeeper/brew/websocket/protocols/protocols.py
pubkeeper/brew/websocket/protocols/legacy/__init__.py
pubkeeper/brew/websocket/protocols/legacy/protocol.py
pubkeeper/brew/websocket/protocols/v1/__init__.py
pubkeeper/brew/websocket/protocols/v1/packet.py
pubkeeper/brew/websocket/protocols/v1/protocol.py
pubkeeper.brew.websocket-1.1.1.dist-info/DESCRIPTION.rst
pubkeeper.brew.websocket-1.1.1.dist-info/METADATA
pubkeeper.brew.websocket-1.1.1.dist-info/RECORD
pubkeeper.brew.websocket-1.1.1.dist-info/WHEEL
pubkeeper.brew.websocket-1.1.1.dist-info/metadata.json
pubkeeper.brew.websocket-1.1.1.dist-info/top_level.txt
