Metadata-Version: 2.0
Name: pubkeeper.brew.websocket
Version: 1.1.1
Summary: Brew, Consume, Websocket
Home-page: http://github.com/pubkeeper/python-brew-websocket
Author: n.io
Author-email: info@n.io
License: UNKNOWN
Keywords: pubkeeper,python-brew-websocket
Platform: UNKNOWN
Classifier: License :: Other/Proprietary License
Classifier: Programming Language :: Python :: 3
Classifier: Programming Language :: Python :: 3.5
Requires-Dist: pubkeeper.client (~=1.1)
Requires-Dist: tornado (~=4.5)
Requires-Dist: ujson
